slackle/__init__.py
slackle/config.py
slackle/constants.py
slackle/exc.py
slackle/core/__init__.py
slackle/core/app.py
slackle/core/dispatcher.py
slackle/core/plugin.py
slackle/core/slack/__init__.py
slackle/core/slack/callback.py
slackle/core/slack/client.py
slackle/core/slack/handler.py
slackle/core/slack/interface.py
slackle/dependencies/__init__.py
slackle/dependencies/builtins.py
slackle/plugins/__init__.py
slackle/plugins/command/__init__.py
slackle/plugins/command/command.py
slackle/plugins/command/dependencies.py
slackle/plugins/command/setup.py
slackle/plugins/command/types.py
slackle/plugins/formatter/__init__.py
slackle/plugins/formatter/formatter.py
slackle/plugins/formatter/setup.py
slackle/plugins/formatter/types.py
slackle/types/__init__.py
slackle/types/context.py
slackle/types/payload.py
slackle/types/response.py
slackle/utils/__init__.py
slackle/utils/slack.py
slackle-0.2.7.dist-info/licenses/LICENSE
slackle-0.2.7.dist-info/METADATA
slackle-0.2.7.dist-info/WHEEL
slackle-0.2.7.dist-info/top_level.txt
slackle-0.2.7.dist-info/RECORD
