Metadata-Version: 2.4
Name: slackle
Version: 0.2.7
Summary: A lightweight Slack bot framework for building modular and maintainable Slack bots.
Author-email: Hosung Lee <hlee24@snu.ac.kr>
License-Expression: MIT
Project-URL: Homepage, https://slackle.dev
Project-URL: Repository, https://github.com/hlee-ai/slackle
Requires-Python: >=3.10
License-File: LICENSE
Requires-Dist: fastapi>=0.115.12
Requires-Dist: pydantic>=2.11.2
Requires-Dist: slack_sdk>=3.35.0
Requires-Dist: starlette>=0.46.1
Provides-Extra: dev
Requires-Dist: black; extra == "dev"
Requires-Dist: isort; extra == "dev"
Requires-Dist: flake8; extra == "dev"
Requires-Dist: pytest; extra == "dev"
Requires-Dist: pytest-cov; extra == "dev"
Requires-Dist: python-multipart; extra == "dev"
Requires-Dist: aiohttp; extra == "dev"
Requires-Dist: pre-commit; extra == "dev"
Requires-Dist: commitizen; extra == "dev"
Dynamic: license-file
